netbox_textdatastore/__init__.py
netbox_textdatastore/filtersets.py
netbox_textdatastore/forms.py
netbox_textdatastore/models.py
netbox_textdatastore/navigation.py
netbox_textdatastore/tables.py
netbox_textdatastore/template_content.py
netbox_textdatastore/urls.py
netbox_textdatastore/views.py
netbox_textdatastore/api/__init__.py
netbox_textdatastore/api/serializers.py
netbox_textdatastore/api/urls.py
netbox_textdatastore/api/views.py
netbox_textdatastore/migrations/0001_initial.py
netbox_textdatastore/migrations/0002_alter_textdataobject_custom_field_data.py
netbox_textdatastore/migrations/__init__.py
netbox_textdatastore/templates/netbox_textdatastore/device_incl.html
netbox_textdatastore/templates/netbox_textdatastore/textdataobject.html
netbox_textdatastore-0.1.0.dist-info/LICENSE
netbox_textdatastore-0.1.0.dist-info/METADATA
netbox_textdatastore-0.1.0.dist-info/WHEEL
netbox_textdatastore-0.1.0.dist-info/top_level.txt
netbox_textdatastore-0.1.0.dist-info/RECORD
