Metadata-Version: 2.1
Name: netbox_textdatastore
Version: 0.1.0
Summary: Netbox Plugin to store textfiles(e.g. configs) alongside devices
Author-email: shrank <info@murxs.ch>
License: Creative Commons Legal Code
Project-URL: Homepage, https://github.com/shrank/netbox_textdatastore
Keywords: network,automation,netbox
Classifier: Programming Language :: Python :: 3
Classifier: Operating System :: OS Independent
Requires-Python: >=3.0
License-File: LICENSE
